ffselect/__init__.py
ffselect/subset.py
ffselect-0.0.1.dist-info/LICENSE
ffselect-0.0.1.dist-info/METADATA
ffselect-0.0.1.dist-info/WHEEL
ffselect-0.0.1.dist-info/top_level.txt
ffselect-0.0.1.dist-info/RECORD
