Metadata-Version: 2.1
Name: ffselect
Version: 0.0.1
Summary: Fast feature subset selection library
Author-email: enaix <enaix@protonmail.com>
License: GNU GENERAL PUBLIC LICENSE
Project-URL: Homepage, https://github.com/enaix/ffselect
Keywords: data-science,machine-learning,feature-selection
Classifier: Programming Language :: Python :: 3
Classifier: Operating System :: OS Independent
Classifier: License :: OSI Approved :: GNU General Public License v3 or later (GPLv3+)
License-File: LICENSE
